bejoor/__init__.py
bejoor/core/__init__.py
bejoor/core/bejoor_algorithm.py
bejoor/core/individual.py
bejoor/diophantine/__init__.py
bejoor/diophantine/diophantine.py
bejoor/diophantine/diophantine_test.py
bejoor/economics_based/__init__.py
bejoor/economics_based/exchange_market_algorithm.py
bejoor/economics_based/exchange_market_algorithm_test.py
bejoor/economics_based/supply_demand_based_optimization.py
bejoor/economics_based/supply_demand_based_optimization_test.py
bejoor/genetic/__init__.py
bejoor/genetic/barnacles_mating_optimizer.py
bejoor/genetic/barnacles_mating_optimizer_test.py
bejoor/genetic/base_genetic.py
bejoor/genetic/base_genetic_test.py
bejoor/genetic/memetic_algorithm.py
bejoor/genetic/memetic_algorithm_test.py
bejoor/genetic/steady_state_genetic_algorithm.py
bejoor/genetic/steady_state_genetic_algorithm_test.py
bejoor/genetic/toy_genetic.py
bejoor/genetic/toy_genetic_test.py
bejoor/physics_based/__init__.py
bejoor/physics_based/electromagnetic_field_optimization.py
bejoor/physics_based/electromagnetic_field_optimization_test.py
bejoor/physics_based/galaxy_based_search_algorithm.py
bejoor/physics_based/galaxy_based_search_algorithm_test.py
bejoor/physics_based/gravitational_search_algorithm.py
bejoor/physics_based/gravitational_search_algorithm_test.py
bejoor/physics_based/simulated_annealing.py
bejoor/physics_based/simulated_annealing_test.py
bejoor/population_based/__init__.py
bejoor/population_based/cuckoo_search.py
bejoor/population_based/differential_evolution.py
bejoor/population_based/differential_evolution_test.py
bejoor/population_based/harmony_search.py
bejoor/population_based/harmony_search_test.py
bejoor/population_based/sine_cosine_algorithm.py
bejoor/population_based/sine_cosine_algorithm_test.py
bejoor/swarm_based/__init__.py
bejoor/swarm_based/artificial_bee_colony.py
bejoor/swarm_based/artificial_bee_colony_test.py
bejoor/swarm_based/bat_algorithm.py
bejoor/swarm_based/bat_algorithm_test.py
bejoor/swarm_based/firefly_algorithm.py
bejoor-0.1.6.dist-info/METADATA
bejoor-0.1.6.dist-info/WHEEL
bejoor-0.1.6.dist-info/top_level.txt
bejoor-0.1.6.dist-info/RECORD
